cowsay_django/__about__.py
cowsay_django/__init__.py
cowsay_django/cowsayer/__init__.py
cowsay_django/cowsayer/admin.py
cowsay_django/cowsayer/apps.py
cowsay_django/cowsayer/models.py
cowsay_django/cowsayer/py.typed
cowsay_django/cowsayer/tests.py
cowsay_django/cowsayer/views.py
cowsay_django/cowsayer/migrations/__init__.py
cowsay_django/cowsayer/templatetags/__init__.py
cowsay_django/cowsayer/templatetags/cowsay_tags.py
cowsay_django-0.0.2.dist-info/METADATA
cowsay_django-0.0.2.dist-info/WHEEL
cowsay_django-0.0.2.dist-info/licenses/LICENSE.txt
cowsay_django-0.0.2.dist-info/RECORD
