Metadata-Version: 2.3
Name: cowsay-django
Version: 0.0.2
Summary: Django app that uses cowsay to render text in a cow bubble.
Project-URL: Documentation, https://kfields.github.io/cowsay-django
Project-URL: Issues, https://github.com/kfields/cowsay-django/issues
Project-URL: Source, https://github.com/kfields/cowsay-django
Author-email: kfields <kurtisfields@gmail.com>
License-Expression: MIT
License-File: LICENSE.txt
Keywords: Django,cowsay
Classifier: Development Status :: 4 - Beta
Classifier: Programming Language :: Python
Classifier: Programming Language :: Python :: 3.8
Classifier: Programming Language :: Python :: 3.9
Classifier: Programming Language :: Python :: 3.10
Classifier: Programming Language :: Python :: 3.11
Classifier: Programming Language :: Python :: 3.12
Classifier: Programming Language :: Python :: Implementation :: CPython
Classifier: Programming Language :: Python :: Implementation :: PyPy
Requires-Python: >=3.8
Requires-Dist: cowsay>=6.1
Requires-Dist: django<6.0,>=3.2
